social_science_ai/__init__.py
social_science_ai/linear_regression/__init__.py
social_science_ai/linear_regression/basic_nodes.py
social_science_ai/linear_regression/generate.py
social_science_ai/linear_regression/linear_regression.py
social_science_ai/linear_regression/propagate.py
social_science_ai/linear_regression/test.py
social_science_ai/linear_regression/visualize.py
ssai/__init__.py
ssai/linear_regression/__init__.py
ssai/linear_regression/basic_nodes.py
ssai/linear_regression/generate.py
ssai/linear_regression/linear_regression.py
ssai/linear_regression/propagate.py
ssai/linear_regression/test.py
ssai/linear_regression/visualize.py
socialscience.ai-0.0.8.dist-info/METADATA
socialscience.ai-0.0.8.dist-info/WHEEL
socialscience.ai-0.0.8.dist-info/top_level.txt
socialscience.ai-0.0.8.dist-info/RECORD
